tokenizer.cpython-38-x86_64-linux-gnu.so
CocCocTokenizer.cpython-38-x86_64-linux-gnu.so
CocCocTokenizer/dicts/special_token.strong
CocCocTokenizer/dicts/keyword.freq
CocCocTokenizer/dicts/syllable_trie.dump
CocCocTokenizer/dicts/Freq2NontoneUniFile
CocCocTokenizer/dicts/d_and_gi.txt
CocCocTokenizer/dicts/vndic_multiterm
CocCocTokenizer/dicts/acronyms
CocCocTokenizer/dicts/nontone_pair_freq_map.dump
CocCocTokenizer/dicts/alphabetic
CocCocTokenizer/dicts/i_and_y.txt
CocCocTokenizer/dicts/nontone_pair_freq
CocCocTokenizer/dicts/numeric
CocCocTokenizer/dicts/chemical_comp
CocCocTokenizer/dicts/multiterm_trie.dump
CocCocTokenizer/dicts/special_token.weak
CocCocTokenizer-0.1.1.dist-info/WHEEL
CocCocTokenizer-0.1.1.dist-info/top_level.txt
CocCocTokenizer-0.1.1.dist-info/METADATA
CocCocTokenizer-0.1.1.dist-info/RECORD
