Metadata-Version: 2.1
Name: CocCocTokenizer
Version: 0.1.1
Summary: CocCocTokenizer deployed by trituenhantao.io.
Home-page: https://trituenhantao.io
License: https://github.com/coccoc/coccoc-tokenizer/blob/master/LICENSE
Requires-Dist: cython
